spender/__init__.py
spender/flow.py
spender/hub.py
spender/hubconf.py
spender/instrument.py
spender/model.py
spender/util.py
spender/data/__init__.py
spender/data/desi.py
spender/data/emission_lines.py
spender/data/sdss.py
spender/data/sky-lines.txt
spender-0.2.8.dist-info/LICENSE
spender-0.2.8.dist-info/METADATA
spender-0.2.8.dist-info/WHEEL
spender-0.2.8.dist-info/top_level.txt
spender-0.2.8.dist-info/RECORD
