Metadata-Version: 2.1
Name: spender
Version: 0.2.8
Summary: Spectrum encoder and decoder
Home-page: https://github.com/pmelchior/spender
Author: Peter Melchior
Author-email: peter.m.melchior@gmail.com
License: MIT
Keywords: spectroscopy,autoencoder
Classifier: Development Status :: 4 - Beta
Classifier: License :: OSI Approved :: MIT License
Classifier: Intended Audience :: Developers
Classifier: Intended Audience :: Education
Classifier: Intended Audience :: Science/Research
Classifier: Operating System :: OS Independent
Classifier: Programming Language :: Python
Classifier: Topic :: Scientific/Engineering :: Astronomy
License-File: LICENSE
Requires-Dist: torch
Requires-Dist: numpy
Requires-Dist: accelerate
Requires-Dist: torchinterp1d
Requires-Dist: astropy
Requires-Dist: humanize
Requires-Dist: psutil
Requires-Dist: GPUtil
Requires-Dist: nflows
